tap_lol/__init__.py
tap_lol/tap_lol.py
tap_lol/schemas/matches.json
tap_lol-0.2.1.dist-info/DESCRIPTION.rst
tap_lol-0.2.1.dist-info/METADATA
tap_lol-0.2.1.dist-info/RECORD
tap_lol-0.2.1.dist-info/WHEEL
tap_lol-0.2.1.dist-info/entry_points.txt
tap_lol-0.2.1.dist-info/metadata.json
tap_lol-0.2.1.dist-info/top_level.txt
