Metadata-Version: 2.0
Name: tap-lol
Version: 0.2.1
Summary: Singer.io tap for extracting data from the League of Legends API
Home-page: https://singer.io
Author: scirner22
Author-email: UNKNOWN
License: UNKNOWN
Platform: UNKNOWN
Classifier: Programming Language :: Python :: 3 :: Only
Requires-Dist: backoff (==1.4.3)
Requires-Dist: pendulum (==1.2.0)
Requires-Dist: requests (==2.12.4)
Requires-Dist: singer-python (==5.0.2)
